MANIFEST.in
README.md
setup.py
net_tools.egg-info/PKG-INFO
net_tools.egg-info/SOURCES.txt
net_tools.egg-info/dependency_links.txt
net_tools.egg-info/entry_points.txt
net_tools.egg-info/requires.txt
net_tools.egg-info/top_level.txt
net_tools.egg-info/zip-safe
nettools/__init__.py
nettools/cli.py
nettools/provider/AwsProvider.py
nettools/provider/Provider.py
nettools/provider/__init__.py
nettools/sensor/__init__.py
nettools/sensor/sensor.py
nettools/utils/__init__.py
nettools/utils/ipv4_utils.py