Metadata-Version: 1.1
Name: net-tools
Version: 0.1.2
Summary: Network measurement tool set for cloud provisioning
Home-page: https://github.com/choonho/net-tools
Author: Choonho Son
Author-email: choonho.son@gmail.com
License: Apache
Keywords: cloud network measurement latency discovery
Platform: UNKNOWN
Classifier: Topic :: Utilities
